better/__init__.py
better/__meta__.py
better/cast.py
better/crypto.py
better/dicts.py
better/enum.py
better/env.py
better/strings.py
better_types-0.0.1.dist-info/WHEEL
better_types-0.0.1.dist-info/METADATA
better_types-0.0.1.dist-info/license_files/LICENSE
better_types-0.0.1.dist-info/RECORD
