Metadata-Version: 2.1
Name: better-types
Version: 0.0.1
Summary: Some improved types and tools for Python
License: MIT
Author-email: Axel H. <noirbizarre@gmail.com>
Requires-Python: >=3.9
Requires-Dist: more-itertools>=8.13.0
Project-URL: repository, https://github.com/noirbizarre/better-types
